humsithon/__init__.py
humsithon-0.0.1.dist-info/LICENSE
humsithon-0.0.1.dist-info/METADATA
humsithon-0.0.1.dist-info/WHEEL
humsithon-0.0.1.dist-info/top_level.txt
humsithon-0.0.1.dist-info/RECORD
