Metadata-Version: 2.1
Name: humsithon
Version: 0.0.1
Summary: سورس حماية مجموعات تليجرام
Home-page: https://github.com/alhomsidev/humsithon
Author: ALHUMSI
Author-email: jjsjs@gmail.com
License: UNKNOWN
Project-URL: Bug Tracker, https://t.me/api_tele
Platform: UNKNOWN
Classifier: Programming Language :: Python :: 3
Classifier: License :: OSI Approved :: MIT License
Classifier: Operating System :: OS Independent
Requires-Python: >=3.6
License-File: LICENSE
